LICENSE
ocpp_asgi/app.py
ocpp_asgi/asgi.py
ocpp_asgi/logging.py
ocpp_asgi/router.py
ocpp_asgi/utils.py
ocpp_asgi-0.4.0.dist-info/LICENSE
ocpp_asgi-0.4.0.dist-info/WHEEL
ocpp_asgi-0.4.0.dist-info/METADATA
ocpp_asgi-0.4.0.dist-info/RECORD
