Metadata-Version: 2.1
Name: ocpp-asgi
Version: 0.4.0
Summary: ocpp-asgi provides ASGI compliant interface for implementing event-driven server-side support for OCPP protocol with Python
Home-page: https://github.com/villekr/ocpp-asgi
License: MIT
Keywords: ocpp,asgi,serverless
Author: Ville Kärkkäinen
Author-email: ville.karkkainen@outlook.com
Requires-Python: >=3.8.1,<4.0.0
Classifier: License :: OSI Approved :: MIT License
Classifier: Programming Language :: Python :: 3
Classifier: Programming Language :: Python :: 3.10
Classifier: Programming Language :: Python :: 3.9
Requires-Dist: ocpp (>=0.15.0,<0.16.0)
